xlibrary/__init__.py
xlibrary/admin.py
xlibrary/apps.py
xlibrary/fields.py
xlibrary/models.py
xlibrary/models1.py
xlibrary/permissions.py
xlibrary/serializers.py
xlibrary/serializers1.py
xlibrary/tests.py
xlibrary/urls.py
xlibrary/utils.py
xlibrary/views.py
xlibrary/views1.py
xlibrary/viewsets.py
xlibrary/migrations/__init__.py
xlibrary/templates/account/password_reset_email.html
xlibrary/templates/registration/password_reset_email.html
xlibrary/templates/reports/report.html
xlibrary/templates/reports/detail/content.html
xlibrary/templates/reports/pagefooter/footer.html
xlibrary/templates/reports/pageheader/column_header.html
xlibrary/templates/reports/pageheader/filters.html
xlibrary/templates/reports/pageheader/header.html
xlibrary/templatetags/__init__.py
xlibrary/templatetags/report_tags.py
xlibrary/templatetags/settings_vars.py
xtrm_library-0.0.20.dist-info/LICENSE.md
xtrm_library-0.0.20.dist-info/LICENSE.txt
xtrm_library-0.0.20.dist-info/METADATA
xtrm_library-0.0.20.dist-info/WHEEL
xtrm_library-0.0.20.dist-info/top_level.txt
xtrm_library-0.0.20.dist-info/RECORD
