Metadata-Version: 2.1
Name: xtrm-library
Version: 0.0.20
Summary: Core library for each project developed by Extreme Solutions
Home-page: 
Author: Extreme Solutions
Author-email: ketan@extremesolutions.in
Classifier: Programming Language :: Python :: 3
Classifier: License :: OSI Approved :: MIT License
Classifier: Operating System :: OS Independent
Requires-Python: >=3.6
License-File: LICENSE.md
License-File: LICENSE.txt
